[
  {
    "name": "Adelaide Street Circuit",
    "map": "https://upload.wikimedia.org/wikipedia/commons/thumb/4/49/Adelaide_%28long_route%29.svg/250px-Adelaide_%28long_route%29.svg.png",
    "trackType": "Street circuit",
    "direction": "Clockwise",
    "location": "Adelaide",
    "country": "Australia",
    "lastLengthKm": "3.780",
    "lastLengthMi": "2.349",
    "turns": "16",
    "grandPrixes": [
      "Australian Grand Prix"
    ],
    "seasons": [
      1985,
      1986,
      1987,
      1988,
      1989,
      1990,
      1991,
      1992,
      1993,
      1994,
      1995
    ],
    "grandPrixesHeld": "11"
  },
  {
    "name": "Ain-Diab Circuit",
    "map": "https://upload.wikimedia.org/wikipedia/commons/thumb/a/a4/Ain-Diab.svg/250px-Ain-Diab.svg.png",
    "trackType": "Road circuit",
    "direction": "Clockwise",
    "location": "Casablanca",
    "country": "Morocco",
    "lastLengthKm": "7.618",
    "lastLengthMi": "4.734",
    "turns": "18",
    "grandPrixes": [
      "Moroccan Grand Prix"
    ],
    "seasons": [
      1958
    ],
    "grandPrixesHeld": "1"
  },
  {
    "name": "Aintree Motor Racing Circuit",
    "map": "https://upload.wikimedia.org/wikipedia/commons/thumb/3/35/Circuit_Aintree.svg/250px-Circuit_Aintree.svg.png",
    "trackType": "Road circuit",
    "direction": "Clockwise",
    "location": "Aintree",
    "country": "United Kingdom",
    "lastLengthKm": "4.828",
    "lastLengthMi": "3.000",
    "turns": "12",
    "grandPrixes": [
      "British Grand Prix"
    ],
    "seasons": [
      1955,
      1957,
      1959,
      1961,
      1962
    ],
    "grandPrixesHeld": "5"
  },
  {
    "name": "Albert Park Circuit ",
    "map": "https://upload.wikimedia.org/wikipedia/commons/thumb/0/0a/Albert_Park_Circuit_2021.svg/250px-Albert_Park_Circuit_2021.svg.png",
    "trackType": "Street circuit",
    "direction": "Clockwise",
    "location": "Melbourne",
    "country": "Australia",
    "lastLengthKm": "5.278",
    "lastLengthMi": "3.280",
    "turns": "16",
    "grandPrixes": [
      "Australian Grand Prix"
    ],
    "seasons": [
      1996,
      1997,
      1998,
      1999,
      2000,
      2001,
      2002,
      2003,
      2004,
      2005,
      2006,
      2007,
      2008,
      2009,
      2010,
      2011,
      2012,
      2013,
      2014,
      2015,
      2016,
      2017,
      2018,
      2019,
      2022,
      2023,
      2024,
      2025
    ],
    "grandPrixesHeld": "28"
  },
  {
    "name": "Algarve International Circuit",
    "map": "https://upload.wikimedia.org/wikipedia/commons/thumb/0/0a/Aut%C3%B3dromo_do_Algarve_F1_Sectors.svg/250px-Aut%C3%B3dromo_do_Algarve_F1_Sectors.svg.png",
    "trackType": "Race circuit",
    "direction": "Clockwise",
    "location": "Portimao",
    "country": "Portugal",
    "lastLengthKm": "4.653",
    "lastLengthMi": "2.891",
    "turns": "15",
    "grandPrixes": [
      "Portuguese Grand Prix"
    ],
    "seasons": [
      2020,
      2021
    ],
    "grandPrixesHeld": "2"
  },
  {
    "name": "Autodromo do Estoril",
    "map": "https://upload.wikimedia.org/wikipedia/commons/thumb/3/34/Aut%C3%B3dromo_de_Estoril_1994-1999.png/250px-Aut%C3%B3dromo_de_Estoril_1994-1999.png",
    "trackType": "Race circuit",
    "direction": "Clockwise",
    "location": "Estoril",
    "country": "Portugal",
    "lastLengthKm": "4.360",
    "lastLengthMi": "2.709",
    "turns": "13",
    "grandPrixes": [
      "Portuguese Grand Prix"
    ],
    "seasons": [
      1984,
      1985,
      1986,
      1987,
      1988,
      1989,
      1990,
      1991,
      1992,
      1993,
      1994,
      1995,
      1996
    ],
    "grandPrixesHeld": "13"
  },
  {
    "name": "Autodromo Hermanos Rodriguez ",
    "map": "https://upload.wikimedia.org/wikipedia/commons/thumb/3/36/Aut%C3%B3dromo_Hermanos_Rodr%C3%ADguez_2015.svg/250px-Aut%C3%B3dromo_Hermanos_Rodr%C3%ADguez_2015.svg.png",
    "trackType": "Race circuit",
    "direction": "Clockwise",
    "location": "Mexico City",
    "country": "Mexico",
    "lastLengthKm": "4.304",
    "lastLengthMi": "2.674",
    "turns": "17",
    "grandPrixes": [
      "Mexican Grand Prix",
      "Mexico City Grand Prix"
    ],
    "seasons": [
      1963,
      1964,
      1965,
      1966,
      1967,
      1968,
      1969,
      1970,
      1986,
      1987,
      1988,
      1989,
      1990,
      1991,
      1992,
      2015,
      2016,
      2017,
      2018,
      2019,
      2021,
      2022,
      2023,
      2024
    ],
    "grandPrixesHeld": "24"
  },
  {
    "name": "Autodromo Internacional do Rio de Janeiro",
    "map": "https://upload.wikimedia.org/wikipedia/commons/thumb/0/08/Aut%C3%B3dromo_de_Jacarepagu%C3%A1_1978-1995.png/250px-Aut%C3%B3dromo_de_Jacarepagu%C3%A1_1978-1995.png",
    "trackType": "Race circuit",
    "direction": "Anti-clockwise",
    "location": "Rio de Janeiro",
    "country": "Brazil",
    "lastLengthKm": "5.031",
    "lastLengthMi": "3.126",
    "turns": "11",
    "grandPrixes": [
      "Brazilian Grand Prix"
    ],
    "seasons": [
      1978,
      1981,
      1982,
      1983,
      1984,
      1985,
      1986,
      1987,
      1988,
      1989
    ],
    "grandPrixesHeld": "10"
  },
  {
    "name": "Autodromo Internazionale del Mugello",
    "map": "https://upload.wikimedia.org/wikipedia/commons/thumb/3/38/Mugello_Racing_Circuit_track_map_15_turns.svg/250px-Mugello_Racing_Circuit_track_map_15_turns.svg.png",
    "trackType": "Race circuit",
    "direction": "Clockwise",
    "location": "Scarperia e San Piero",
    "country": "Italy",
    "lastLengthKm": "5.245",
    "lastLengthMi": "3.259",
    "turns": "14",
    "grandPrixes": [
      "Tuscan Grand Prix"
    ],
    "seasons": [
      2020
    ],
    "grandPrixesHeld": "1"
  },
  {
    "name": "Autodromo Internazionale Enzo e Dino Ferrari ",
    "map": "https://upload.wikimedia.org/wikipedia/commons/thumb/2/22/Imola_2009.svg/250px-Imola_2009.svg.png",
    "trackType": "Race circuit",
    "direction": "Anti-clockwise",
    "location": "Imola",
    "country": "Italy",
    "lastLengthKm": "4.909",
    "lastLengthMi": "3.050",
    "turns": "17",
    "grandPrixes": [
      "Italian Grand Prix",
      "San Marino Grand Prix",
      "Emilia Romagna Grand Prix"
    ],
    "seasons": [
      1980,
      1981,
      1982,
      1983,
      1984,
      1985,
      1986,
      1987,
      1988,
      1989,
      1990,
      1991,
      1992,
      1993,
      1994,
      1995,
      1996,
      1997,
      1998,
      1999,
      2000,
      2001,
      2002,
      2003,
      2004,
      2005,
      2006,
      2020,
      2021,
      2022,
      2024,
      2025
    ],
    "grandPrixesHeld": "32"
  },
  {
    "name": "Autodromo Jose Carlos Pace ",
    "map": "https://upload.wikimedia.org/wikipedia/commons/thumb/c/cf/Aut%C3%B3dromo_Jos%C3%A9_Carlos_Pace_%28AKA_Interlagos%29_track_map.svg/250px-Aut%C3%B3dromo_Jos%C3%A9_Carlos_Pace_%28AKA_Interlagos%29_track_map.svg.png",
    "trackType": "Race circuit",
    "direction": "Anti-clockwise",
    "location": "Sao Paulo",
    "country": "Brazil",
    "lastLengthKm": "4.309",
    "lastLengthMi": "2.677",
    "turns": "15",
    "grandPrixes": [
      "Brazilian Grand Prix",
      "Sao Paulo Grand Prix"
    ],
    "seasons": [
      1973,
      1974,
      1975,
      1976,
      1977,
      1979,
      1980,
      1990,
      1991,
      1992,
      1993,
      1994,
      1995,
      1996,
      1997,
      1998,
      1999,
      2000,
      2001,
      2002,
      2003,
      2004,
      2005,
      2006,
      2007,
      2008,
      2009,
      2010,
      2011,
      2012,
      2013,
      2014,
      2015,
      2016,
      2017,
      2018,
      2019,
      2021,
      2022,
      2023,
      2024
    ],
    "grandPrixesHeld": "41"
  },
  {
    "name": "Autodromo Nazionale di Monza ",
    "map": "https://upload.wikimedia.org/wikipedia/commons/thumb/f/f8/Monza_track_map.svg/250px-Monza_track_map.svg.png",
    "trackType": "Race circuit",
    "direction": "Clockwise",
    "location": "Monza",
    "country": "Italy",
    "lastLengthKm": "5.793",
    "lastLengthMi": "3.600",
    "turns": "11",
    "grandPrixes": [
      "Italian Grand Prix"
    ],
    "seasons": [
      1950,
      1951,
      1952,
      1953,
      1954,
      1955,
      1956,
      1957,
      1958,
      1959,
      1960,
      1961,
      1962,
      1963,
      1964,
      1965,
      1966,
      1967,
      1968,
      1969,
      1970,
      1971,
      1972,
      1973,
      1974,
      1975,
      1976,
      1977,
      1978,
      1979,
      1981,
      1982,
      1983,
      1984,
      1985,
      1986,
      1987,
      1988,
      1989,
      1990,
      1991,
      1992,
      1993,
      1994,
      1995,
      1996,
      1997,
      1998,
      1999,
      2000,
      2001,
      2002,
      2003,
      2004,
      2005,
      2006,
      2007,
      2008,
      2009,
      2010,
      2011,
      2012,
      2013,
      2014,
      2015,
      2016,
      2017,
      2018,
      2019,
      2020,
      2021,
      2022,
      2023,
      2024
    ],
    "grandPrixesHeld": "74"
  },
  {
    "name": "Autodromo Oscar y Juan Galvez",
    "map": "https://upload.wikimedia.org/wikipedia/commons/thumb/c/c6/Aut%C3%B3dromo_Oscar_y_Juan_G%C3%A1lvez_Circuito_N%C2%B0_6_por_Senna.svg/250px-Aut%C3%B3dromo_Oscar_y_Juan_G%C3%A1lvez_Circuito_N%C2%B0_6_por_Senna.svg.png",
    "trackType": "Race circuit",
    "direction": "Clockwise",
    "location": "Buenos Aires",
    "country": "Argentina",
    "lastLengthKm": "4.259",
    "lastLengthMi": "2.646",
    "turns": "18",
    "grandPrixes": [
      "Argentine Grand Prix"
    ],
    "seasons": [
      1953,
      1954,
      1955,
      1956,
      1957,
      1958,
      1960,
      1972,
      1973,
      1974,
      1975,
      1977,
      1978,
      1979,
      1980,
      1981,
      1995,
      1996,
      1997,
      1998
    ],
    "grandPrixesHeld": "20"
  },
  {
    "name": "AVUS",
    "map": "https://upload.wikimedia.org/wikipedia/commons/thumb/6/6d/Circuit_AVUS.svg/250px-Circuit_AVUS.svg.png",
    "trackType": "Road circuit",
    "direction": "Anti-clockwise",
    "location": "Berlin",
    "country": "Germany",
    "lastLengthKm": "8.300",
    "lastLengthMi": "5.157",
    "turns": "4",
    "grandPrixes": [
      "German Grand Prix"
    ],
    "seasons": [
      1959
    ],
    "grandPrixesHeld": "1"
  },
  {
    "name": "Bahrain International Circuit ",
    "map": "https://upload.wikimedia.org/wikipedia/commons/thumb/2/29/Bahrain_International_Circuit--Grand_Prix_Layout.svg/250px-Bahrain_International_Circuit--Grand_Prix_Layout.svg.png",
    "trackType": "Race circuit",
    "direction": "Clockwise",
    "location": "Sakhir",
    "country": "Bahrain",
    "lastLengthKm": "5.412",
    "lastLengthMi": "3.363",
    "turns": "15",
    "grandPrixes": [
      "Bahrain Grand Prix",
      "Sakhir Grand Prix"
    ],
    "seasons": [
      2004,
      2005,
      2006,
      2007,
      2008,
      2009,
      2010,
      2012,
      2013,
      2014,
      2015,
      2016,
      2017,
      2018,
      2019,
      2020,
      2021,
      2022,
      2023,
      2024,
      2025
    ],
    "grandPrixesHeld": "22"
  },
  {
    "name": "Baku City Circuit ",
    "map": "https://upload.wikimedia.org/wikipedia/commons/thumb/f/f1/Baku_Formula_One_circuit_map.svg/250px-Baku_Formula_One_circuit_map.svg.png",
    "trackType": "Street circuit",
    "direction": "Anti-clockwise",
    "location": "Baku",
    "country": "Azerbaijan",
    "lastLengthKm": "6.003",
    "lastLengthMi": "3.730",
    "turns": "20",
    "grandPrixes": [
      "European Grand Prix",
      "Azerbaijan Grand Prix"
    ],
    "seasons": [
      2016,
      2017,
      2018,
      2019,
      2021,
      2022,
      2023,
      2024
    ],
    "grandPrixesHeld": "8"
  },
  {
    "name": "Brands Hatch Circuit",
    "map": "https://upload.wikimedia.org/wikipedia/commons/thumb/4/45/Brands_Hatch_1976-1987.svg/250px-Brands_Hatch_1976-1987.svg.png",
    "trackType": "Race circuit",
    "direction": "Clockwise",
    "location": "West Kingsdown",
    "country": "United Kingdom",
    "lastLengthKm": "4.206",
    "lastLengthMi": "2.613",
    "turns": "11",
    "grandPrixes": [
      "British Grand Prix",
      "European Grand Prix"
    ],
    "seasons": [
      1964,
      1966,
      1968,
      1970,
      1972,
      1974,
      1976,
      1978,
      1980,
      1982,
      1983,
      1984,
      1985,
      1986
    ],
    "grandPrixesHeld": "14"
  },
  {
    "name": "Buddh International Circuit",
    "map": "https://upload.wikimedia.org/wikipedia/commons/thumb/2/26/Buddh_Circuit_1.svg/250px-Buddh_Circuit_1.svg.png",
    "trackType": "Race circuit",
    "direction": "Clockwise",
    "location": "Greater Noida",
    "country": "India",
    "lastLengthKm": "5.141",
    "lastLengthMi": "3.194",
    "turns": "16",
    "grandPrixes": [
      "Indian Grand Prix"
    ],
    "seasons": [
      2011,
      2012,
      2013
    ],
    "grandPrixesHeld": "3"
  },
  {
    "name": "Bugatti Au Mans",
    "map": "https://upload.wikimedia.org/wikipedia/commons/thumb/d/d5/Circuit_Le_Mans_Bugatti.png/250px-Circuit_Le_Mans_Bugatti.png",
    "trackType": "Race circuit",
    "direction": "Clockwise",
    "location": "Le Mans",
    "country": "France",
    "lastLengthKm": "4.430",
    "lastLengthMi": "2.753",
    "turns": "8",
    "grandPrixes": [
      "French Grand Prix"
    ],
    "seasons": [
      1967
    ],
    "grandPrixesHeld": "1"
  },
  {
    "name": "Caesars Palace Grand Prix Circuit",
    "map": "https://upload.wikimedia.org/wikipedia/commons/thumb/f/fa/Circuit_Caesars_Palace.png/250px-Circuit_Caesars_Palace.png",
    "trackType": "Street circuit",
    "direction": "Anti-clockwise",
    "location": "Paradise",
    "country": "United States",
    "lastLengthKm": "3.650",
    "lastLengthMi": "2.268",
    "turns": "14",
    "grandPrixes": [
      "Caesars Palace Grand Prix"
    ],
    "seasons": [
      1981,
      1982
    ],
    "grandPrixesHeld": "2"
  },
  {
    "name": "Charade Circuit",
    "map": "https://upload.wikimedia.org/wikipedia/commons/thumb/c/ce/Circuit_Charade_1958_1988.png/250px-Circuit_Charade_1958_1988.png",
    "trackType": "Road circuit",
    "direction": "Clockwise",
    "location": "Saint-Genes-Champanelle",
    "country": "France",
    "lastLengthKm": "8.055",
    "lastLengthMi": "5.005",
    "turns": "38",
    "grandPrixes": [
      "French Grand Prix"
    ],
    "seasons": [
      1965,
      1969,
      1970,
      1972
    ],
    "grandPrixesHeld": "4"
  },
  {
    "name": "Circuit Bremgarten",
    "map": "https://upload.wikimedia.org/wikipedia/commons/thumb/e/e7/Circuit_Bremgarten.svg/250px-Circuit_Bremgarten.svg.png",
    "trackType": "Road circuit",
    "direction": "Clockwise",
    "location": "Bern",
    "country": "Switzerland",
    "lastLengthKm": "7.208",
    "lastLengthMi": "4.479",
    "turns": "14",
    "grandPrixes": [
      "Swiss Grand Prix"
    ],
    "seasons": [
      1950,
      1951,
      1952,
      1953,
      1954
    ],
    "grandPrixesHeld": "5"
  },
  {
    "name": "Circuit de Barcelona-Catalunya ",
    "map": "https://upload.wikimedia.org/wikipedia/commons/thumb/8/87/Circuit_de_Catalunya_moto_2021.svg/250px-Circuit_de_Catalunya_moto_2021.svg.png",
    "trackType": "Race circuit",
    "direction": "Clockwise",
    "location": "Montmelo",
    "country": "Spain",
    "lastLengthKm": "4.657",
    "lastLengthMi": "2.894",
    "turns": "14",
    "grandPrixes": [
      "Spanish Grand Prix"
    ],
    "seasons": [
      1991,
      1992,
      1993,
      1994,
      1995,
      1996,
      1997,
      1998,
      1999,
      2000,
      2001,
      2002,
      2003,
      2004,
      2005,
      2006,
      2007,
      2008,
      2009,
      2010,
      2011,
      2012,
      2013,
      2014,
      2015,
      2016,
      2017,
      2018,
      2019,
      2020,
      2021,
      2022,
      2023,
      2024
    ],
    "grandPrixesHeld": "34"
  },
  {
    "name": "Circuit de Monaco ",
    "map": "https://upload.wikimedia.org/wikipedia/commons/thumb/3/36/Monte_Carlo_Formula_1_track_map.svg/250px-Monte_Carlo_Formula_1_track_map.svg.png",
    "trackType": "Street circuit",
    "direction": "Clockwise",
    "location": "Monte Carlo",
    "country": "Monaco",
    "lastLengthKm": "3.337",
    "lastLengthMi": "2.074",
    "turns": "19",
    "grandPrixes": [
      "Monaco Grand Prix"
    ],
    "seasons": [
      1950,
      1955,
      1956,
      1957,
      1958,
      1959,
      1960,
      1961,
      1962,
      1963,
      1964,
      1965,
      1966,
      1967,
      1968,
      1969,
      1970,
      1971,
      1972,
      1973,
      1974,
      1975,
      1976,
      1977,
      1978,
      1979,
      1980,
      1981,
      1982,
      1983,
      1984,
      1985,
      1986,
      1987,
      1988,
      1989,
      1990,
      1991,
      1992,
      1993,
      1994,
      1995,
      1996,
      1997,
      1998,
      1999,
      2000,
      2001,
      2002,
      2003,
      2004,
      2005,
      2006,
      2007,
      2008,
      2009,
      2010,
      2011,
      2012,
      2013,
      2014,
      2015,
      2016,
      2017,
      2018,
      2019,
      2021,
      2022,
      2023,
      2024
    ],
    "grandPrixesHeld": "70"
  },
  {
    "name": "Circuit de Nevers Magny-Cours",
    "map": "https://upload.wikimedia.org/wikipedia/commons/thumb/8/87/Circuit_de_Nevers_Magny-Cours.svg/250px-Circuit_de_Nevers_Magny-Cours.svg.png",
    "trackType": "Race circuit",
    "direction": "Clockwise",
    "location": "Magny-Cours",
    "country": "France",
    "lastLengthKm": "4.411",
    "lastLengthMi": "2.741",
    "turns": "16",
    "grandPrixes": [
      "French Grand Prix"
    ],
    "seasons": [
      1991,
      1992,
      1993,
      1994,
      1995,
      1996,
      1997,
      1998,
      1999,
      2000,
      2001,
      2002,
      2003,
      2004,
      2005,
      2006,
      2007,
      2008
    ],
    "grandPrixesHeld": "18"
  },
  {
    "name": "Circuit de Pedralbes",
    "map": "https://upload.wikimedia.org/wikipedia/commons/thumb/5/59/Circuit_Pedralbes.png/250px-Circuit_Pedralbes.png",
    "trackType": "Street circuit",
    "direction": "Clockwise",
    "location": "Barcelona",
    "country": "Spain",
    "lastLengthKm": "6.316",
    "lastLengthMi": "3.925",
    "turns": "6",
    "grandPrixes": [
      "Spanish Grand Prix"
    ],
    "seasons": [
      1951,
      1954
    ],
    "grandPrixesHeld": "2"
  },
  {
    "name": "Circuit de Reims-Gueux",
    "map": "https://upload.wikimedia.org/wikipedia/commons/thumb/f/fa/Circuit-Reims-1954.png/250px-Circuit-Reims-1954.png",
    "trackType": "Road circuit",
    "direction": "Clockwise",
    "location": "Gueux",
    "country": "France",
    "lastLengthKm": "8.302",
    "lastLengthMi": "5.159",
    "turns": "6",
    "grandPrixes": [
      "French Grand Prix"
    ],
    "seasons": [
      1950,
      1951,
      1953,
      1954,
      1956,
      1958,
      1959,
      1960,
      1961,
      1963,
      1966
    ],
    "grandPrixesHeld": "11"
  },
  {
    "name": "Circuit de Spa-Francorchamps ",
    "map": "https://upload.wikimedia.org/wikipedia/commons/thumb/5/54/Spa-Francorchamps_of_Belgium.svg/250px-Spa-Francorchamps_of_Belgium.svg.png",
    "trackType": "Race circuit",
    "direction": "Clockwise",
    "location": "Stavelot",
    "country": "Belgium",
    "lastLengthKm": "7.004",
    "lastLengthMi": "4.352",
    "turns": "20",
    "grandPrixes": [
      "Belgian Grand Prix"
    ],
    "seasons": [
      1950,
      1951,
      1952,
      1953,
      1954,
      1955,
      1956,
      1958,
      1960,
      1961,
      1962,
      1963,
      1964,
      1965,
      1966,
      1967,
      1968,
      1970,
      1983,
      1985,
      1986,
      1987,
      1988,
      1989,
      1990,
      1991,
      1992,
      1993,
      1994,
      1995,
      1996,
      1997,
      1998,
      1999,
      2000,
      2001,
      2002,
      2004,
      2005,
      2007,
      2008,
      2009,
      2010,
      2011,
      2012,
      2013,
      2014,
      2015,
      2016,
      2017,
      2018,
      2019,
      2020,
      2021,
      2022,
      2023,
      2024
    ],
    "grandPrixesHeld": "57"
  },
  {
    "name": "Circuit Dijon-Prenois",
    "map": "https://upload.wikimedia.org/wikipedia/commons/thumb/d/de/Dijon-Prenois_Circuit.svg/250px-Dijon-Prenois_Circuit.svg.png",
    "trackType": "Race circuit",
    "direction": "Clockwise",
    "location": "Prenois",
    "country": "France",
    "lastLengthKm": "3.886",
    "lastLengthMi": "2.415",
    "turns": "12",
    "grandPrixes": [
      "French Grand Prix",
      "Swiss Grand Prix"
    ],
    "seasons": [
      1974,
      1977,
      1979,
      1981,
      1982,
      1984
    ],
    "grandPrixesHeld": "6"
  },
  {
    "name": "Circuit Gilles-Villeneuve ",
    "map": "https://upload.wikimedia.org/wikipedia/commons/thumb/f/f9/%C3%8Ele_Notre-Dame_%28Circuit_Gilles_Villeneuve%29.svg/250px-%C3%8Ele_Notre-Dame_%28Circuit_Gilles_Villeneuve%29.svg.png",
    "trackType": "Street circuit",
    "direction": "Clockwise",
    "location": "Montreal",
    "country": "Canada",
    "lastLengthKm": "4.361",
    "lastLengthMi": "2.710",
    "turns": "13",
    "grandPrixes": [
      "Canadian Grand Prix"
    ],
    "seasons": [
      1978,
      1979,
      1980,
      1981,
      1982,
      1983,
      1984,
      1985,
      1986,
      1988,
      1989,
      1990,
      1991,
      1992,
      1993,
      1994,
      1995,
      1996,
      1997,
      1998,
      1999,
      2000,
      2001,
      2002,
      2003,
      2004,
      2005,
      2006,
      2007,
      2008,
      2010,
      2011,
      2012,
      2013,
      2014,
      2015,
      2016,
      2017,
      2018,
      2019,
      2022,
      2023,
      2024
    ],
    "grandPrixesHeld": "43"
  },
  {
    "name": "Circuit Mont-Tremblant",
    "map": "https://upload.wikimedia.org/wikipedia/commons/thumb/1/14/Circuit_Mont_Tremblant.png/250px-Circuit_Mont_Tremblant.png",
    "trackType": "Race circuit",
    "direction": "Clockwise",
    "location": "Mont-Tremblant",
    "country": "Canada",
    "lastLengthKm": "4.265",
    "lastLengthMi": "2.650",
    "turns": "15",
    "grandPrixes": [
      "Canadian Grand Prix"
    ],
    "seasons": [
      1968,
      1970
    ],
    "grandPrixesHeld": "2"
  },
  {
    "name": "Circuit of the Americas ",
    "map": "https://upload.wikimedia.org/wikipedia/commons/thumb/a/a5/Austin_circuit.svg/250px-Austin_circuit.svg.png",
    "trackType": "Race circuit",
    "direction": "Anti-clockwise",
    "location": "Austin",
    "country": "United States",
    "lastLengthKm": "5.513",
    "lastLengthMi": "3.426",
    "turns": "20",
    "grandPrixes": [
      "United States Grand Prix"
    ],
    "seasons": [
      2012,
      2013,
      2014,
      2015,
      2016,
      2017,
      2018,
      2019,
      2021,
      2022,
      2023,
      2024
    ],
    "grandPrixesHeld": "12"
  },
  {
    "name": "Circuit Paul Ricard",
    "map": "https://upload.wikimedia.org/wikipedia/commons/thumb/f/f2/Le_Castellet_circuit_map_Formula_One_2019_and_2021_with_corner_names_English_19_07_2021.svg/250px-Le_Castellet_circuit_map_Formula_One_2019_and_2021_with_corner_names_English_19_07_2021.svg.png",
    "trackType": "Race circuit",
    "direction": "Clockwise",
    "location": "Le Castellet",
    "country": "France",
    "lastLengthKm": "5.842",
    "lastLengthMi": "3.630",
    "turns": "15",
    "grandPrixes": [
      "French Grand Prix"
    ],
    "seasons": [
      1971,
      1973,
      1975,
      1976,
      1978,
      1980,
      1982,
      1983,
      1985,
      1986,
      1987,
      1988,
      1989,
      1990,
      2018,
      2019,
      2021,
      2022
    ],
    "grandPrixesHeld": "18"
  },
  {
    "name": "Circuit Zandvoort ",
    "map": "https://upload.wikimedia.org/wikipedia/commons/thumb/7/78/Zandvoort_Circuit.png/250px-Zandvoort_Circuit.png",
    "trackType": "Race circuit",
    "direction": "Clockwise",
    "location": "Zandvoort",
    "country": "Netherlands",
    "lastLengthKm": "4.259",
    "lastLengthMi": "2.646",
    "turns": "14",
    "grandPrixes": [
      "Dutch Grand Prix"
    ],
    "seasons": [
      1952,
      1953,
      1955,
      1958,
      1959,
      1960,
      1961,
      1962,
      1963,
      1964,
      1965,
      1966,
      1967,
      1968,
      1969,
      1970,
      1971,
      1973,
      1974,
      1975,
      1976,
      1977,
      1978,
      1979,
      1980,
      1981,
      1982,
      1983,
      1984,
      1985,
      2021,
      2022,
      2023,
      2024
    ],
    "grandPrixesHeld": "34"
  },
  {
    "name": "Circuit Zolder",
    "map": "https://upload.wikimedia.org/wikipedia/commons/thumb/c/cb/Circuit_Zolder-1975-1985.svg/250px-Circuit_Zolder-1975-1985.svg.png",
    "trackType": "Race circuit",
    "direction": "Clockwise",
    "location": "Heusden-Zolder",
    "country": "Belgium",
    "lastLengthKm": "4.262",
    "lastLengthMi": "2.648",
    "turns": "10",
    "grandPrixes": [
      "Belgian Grand Prix"
    ],
    "seasons": [
      1973,
      1975,
      1976,
      1977,
      1978,
      1979,
      1980,
      1981,
      1982,
      1984
    ],
    "grandPrixesHeld": "10"
  },
  {
    "name": "Circuito da Boavista",
    "map": "https://upload.wikimedia.org/wikipedia/commons/thumb/e/ea/Boavista_%28Oporto%29.svg/250px-Boavista_%28Oporto%29.svg.png",
    "trackType": "Street circuit",
    "direction": "Anti-clockwise",
    "location": "Porto",
    "country": "Portugal",
    "lastLengthKm": "7.775",
    "lastLengthMi": "4.831",
    "turns": "15",
    "grandPrixes": [
      "Portuguese Grand Prix"
    ],
    "seasons": [
      1958,
      1960
    ],
    "grandPrixesHeld": "2"
  },
  {
    "name": "Circuito de Monsanto",
    "map": "https://upload.wikimedia.org/wikipedia/commons/thumb/d/de/Circuit_Monsanto.png/250px-Circuit_Monsanto.png",
    "trackType": "Street circuit",
    "direction": "Clockwise",
    "location": "Lisbon",
    "country": "Portugal",
    "lastLengthKm": "5.440",
    "lastLengthMi": "3.380",
    "turns": "9",
    "grandPrixes": [
      "Portuguese Grand Prix"
    ],
    "seasons": [
      1959
    ],
    "grandPrixesHeld": "1"
  },
  {
    "name": "Circuito Permanente de Jerez",
    "map": "https://upload.wikimedia.org/wikipedia/commons/thumb/b/bc/Jerez_Grand_prix_Circuit_1994-2003.svg/250px-Jerez_Grand_prix_Circuit_1994-2003.svg.png",
    "trackType": "Race circuit",
    "direction": "Clockwise",
    "location": "Jerez de la Frontera",
    "country": "Spain",
    "lastLengthKm": "4.428",
    "lastLengthMi": "2.751",
    "turns": "13",
    "grandPrixes": [
      "Spanish Grand Prix",
      "European Grand Prix"
    ],
    "seasons": [
      1986,
      1987,
      1988,
      1989,
      1990,
      1994,
      1997
    ],
    "grandPrixesHeld": "7"
  },
  {
    "name": "Circuito Permanente del Jarama",
    "map": "https://upload.wikimedia.org/wikipedia/commons/thumb/a/a4/Circuito_Permanente_del_Jarama_1980.svg/250px-Circuito_Permanente_del_Jarama_1980.svg.png",
    "trackType": "Race circuit",
    "direction": "Clockwise",
    "location": "San Sebastian de los Reyes",
    "country": "Spain",
    "lastLengthKm": "3.314",
    "lastLengthMi": "2.059",
    "turns": "12",
    "grandPrixes": [
      "Spanish Grand Prix"
    ],
    "seasons": [
      1968,
      1970,
      1972,
      1974,
      1976,
      1977,
      1978,
      1979,
      1981
    ],
    "grandPrixesHeld": "9"
  },
  {
    "name": "Dallas Fair Park",
    "map": "https://upload.wikimedia.org/wikipedia/commons/thumb/5/58/Circuit_Fair_Park.svg/250px-Circuit_Fair_Park.svg.png",
    "trackType": "Street circuit",
    "direction": "Anti-clockwise",
    "location": "Dallas",
    "country": "United States",
    "lastLengthKm": "3.901",
    "lastLengthMi": "2.424",
    "turns": "14",
    "grandPrixes": [
      "Dallas Grand Prix"
    ],
    "seasons": [
      1984
    ],
    "grandPrixesHeld": "1"
  },
  {
    "name": "Detroit Street Circuit",
    "map": "https://upload.wikimedia.org/wikipedia/commons/thumb/3/38/Downtown_Detroit_Street_Circuit.svg/250px-Downtown_Detroit_Street_Circuit.svg.png",
    "trackType": "Street circuit",
    "direction": "Anti-clockwise",
    "location": "Detroit",
    "country": "United States",
    "lastLengthKm": "4.023",
    "lastLengthMi": "2.500",
    "turns": "20",
    "grandPrixes": [
      "Detroit Grand Prix"
    ],
    "seasons": [
      1982,
      1983,
      1984,
      1985,
      1986,
      1987,
      1988
    ],
    "grandPrixesHeld": "7"
  },
  {
    "name": "Donington Park",
    "map": "https://upload.wikimedia.org/wikipedia/commons/thumb/9/9b/Donington_as_of_2006.svg/250px-Donington_as_of_2006.svg.png",
    "trackType": "Race circuit",
    "direction": "Clockwise",
    "location": "Castle Donington",
    "country": "United Kingdom",
    "lastLengthKm": "4.020",
    "lastLengthMi": "2.498",
    "turns": "11",
    "grandPrixes": [
      "European Grand Prix"
    ],
    "seasons": [
      1993
    ],
    "grandPrixesHeld": "1"
  },
  {
    "name": "Fuji Speedway",
    "map": "https://upload.wikimedia.org/wikipedia/commons/thumb/2/2c/Fuji.svg/250px-Fuji.svg.png",
    "trackType": "Race circuit",
    "direction": "Clockwise",
    "location": "Oyama",
    "country": "Japan",
    "lastLengthKm": "4.563",
    "lastLengthMi": "2.835",
    "turns": "16",
    "grandPrixes": [
      "Japanese Grand Prix"
    ],
    "seasons": [
      1976,
      1977,
      2007,
      2008
    ],
    "grandPrixesHeld": "4"
  },
  {
    "name": "Hockenheimring",
    "map": "https://upload.wikimedia.org/wikipedia/commons/thumb/e/e5/Hockenheim2012.svg/250px-Hockenheim2012.svg.png",
    "trackType": "Race circuit",
    "direction": "Clockwise",
    "location": "Hockenheim",
    "country": "Germany",
    "lastLengthKm": "4.574",
    "lastLengthMi": "2.842",
    "turns": "16",
    "grandPrixes": [
      "German Grand Prix"
    ],
    "seasons": [
      1970,
      1977,
      1978,
      1979,
      1980,
      1981,
      1982,
      1983,
      1984,
      1986,
      1987,
      1988,
      1989,
      1990,
      1991,
      1992,
      1993,
      1994,
      1995,
      1996,
      1997,
      1998,
      1999,
      2000,
      2001,
      2002,
      2003,
      2004,
      2005,
      2006,
      2008,
      2010,
      2012,
      2014,
      2016,
      2018,
      2019
    ],
    "grandPrixesHeld": "37"
  },
  {
    "name": "Hungaroring ",
    "map": "https://upload.wikimedia.org/wikipedia/commons/thumb/9/91/Hungaroring.svg/250px-Hungaroring.svg.png",
    "trackType": "Race circuit",
    "direction": "Clockwise",
    "location": "Mogyorod",
    "country": "Hungary",
    "lastLengthKm": "4.381",
    "lastLengthMi": "2.722",
    "turns": "14",
    "grandPrixes": [
      "Hungarian Grand Prix"
    ],
    "seasons": [
      1986,
      1987,
      1988,
      1989,
      1990,
      1991,
      1992,
      1993,
      1994,
      1995,
      1996,
      1997,
      1998,
      1999,
      2000,
      2001,
      2002,
      2003,
      2004,
      2005,
      2006,
      2007,
      2008,
      2009,
      2010,
      2011,
      2012,
      2013,
      2014,
      2015,
      2016,
      2017,
      2018,
      2019,
      2020,
      2021,
      2022,
      2023,
      2024
    ],
    "grandPrixesHeld": "39"
  },
  {
    "name": "Indianapolis Motor Speedway",
    "map": "https://upload.wikimedia.org/wikipedia/commons/thumb/a/a1/Indianapolis_Motor_Speedway_-_road_course.svg/250px-Indianapolis_Motor_Speedway_-_road_course.svg.png",
    "trackType": "Race circuit",
    "direction": "Clockwise",
    "location": "Speedway",
    "country": "United States",
    "lastLengthKm": "4.192",
    "lastLengthMi": "2.605",
    "turns": "13",
    "grandPrixes": [
      "Indianapolis 500",
      "United States Grand Prix"
    ],
    "seasons": [
      1950,
      1951,
      1952,
      1953,
      1954,
      1955,
      1956,
      1957,
      1958,
      1959,
      1960,
      2000,
      2001,
      2002,
      2003,
      2004,
      2005,
      2006,
      2007
    ],
    "grandPrixesHeld": "19"
  },
  {
    "name": "Intercity Istanbul Park",
    "map": "https://upload.wikimedia.org/wikipedia/commons/thumb/5/5d/Istanbul_park.svg/250px-Istanbul_park.svg.png",
    "trackType": "Race circuit",
    "direction": "Anti-clockwise",
    "location": "Istanbul",
    "country": "Turkey",
    "lastLengthKm": "5.338",
    "lastLengthMi": "3.317",
    "turns": "14",
    "grandPrixes": [
      "Turkish Grand Prix"
    ],
    "seasons": [
      2005,
      2006,
      2007,
      2008,
      2009,
      2010,
      2011,
      2020,
      2021
    ],
    "grandPrixesHeld": "9"
  },
  {
    "name": "Jeddah Corniche Circuit ",
    "map": "https://upload.wikimedia.org/wikipedia/commons/thumb/4/4c/Jeddah_Street_Circuit_2021.svg/250px-Jeddah_Street_Circuit_2021.svg.png",
    "trackType": "Street circuit",
    "direction": "Anti-clockwise",
    "location": "Jeddah",
    "country": "Saudi Arabia",
    "lastLengthKm": "6.174",
    "lastLengthMi": "3.836",
    "turns": "27",
    "grandPrixes": [
      "Saudi Arabian Grand Prix"
    ],
    "seasons": [
      2021,
      2022,
      2023,
      2024,
      2025
    ],
    "grandPrixesHeld": "5"
  },
  {
    "name": "Korea International Circuit",
    "map": "https://upload.wikimedia.org/wikipedia/commons/thumb/2/29/Korea_international_circuit_v3.svg/250px-Korea_international_circuit_v3.svg.png",
    "trackType": "Race circuit",
    "direction": "Anti-clockwise",
    "location": "Yeongam",
    "country": "South Korea",
    "lastLengthKm": "5.615",
    "lastLengthMi": "3.489",
    "turns": "18",
    "grandPrixes": [
      "Korean Grand Prix"
    ],
    "seasons": [
      2010,
      2011,
      2012,
      2013
    ],
    "grandPrixesHeld": "4"
  },
  {
    "name": "Kyalami Grand Prix Circuit",
    "map": "https://upload.wikimedia.org/wikipedia/commons/thumb/0/0e/Kyalami_1992_Layout.png/250px-Kyalami_1992_Layout.png",
    "trackType": "Race circuit",
    "direction": "Anti-clockwise",
    "location": "Midrand",
    "country": "South Africa",
    "lastLengthKm": "4.261",
    "lastLengthMi": "2.648",
    "turns": "13",
    "grandPrixes": [
      "South African Grand Prix"
    ],
    "seasons": [
      1967,
      1968,
      1969,
      1970,
      1971,
      1972,
      1973,
      1974,
      1975,
      1976,
      1977,
      1978,
      1979,
      1980,
      1982,
      1983,
      1984,
      1985,
      1992,
      1993
    ],
    "grandPrixesHeld": "20"
  },
  {
    "name": "Las Vegas Strip Circuit ",
    "map": "https://upload.wikimedia.org/wikipedia/commons/thumb/f/ff/Las_Vegas_Strip_Circuit_2023.png/250px-Las_Vegas_Strip_Circuit_2023.png",
    "trackType": "Street circuit",
    "direction": "Anti-clockwise",
    "location": "Paradise",
    "country": "United States",
    "lastLengthKm": "6.201",
    "lastLengthMi": "3.853",
    "turns": "17",
    "grandPrixes": [
      "Las Vegas Grand Prix"
    ],
    "seasons": [
      2023,
      2024
    ],
    "grandPrixesHeld": "2"
  },
  {
    "name": "Long Beach Street Circuit",
    "map": "https://upload.wikimedia.org/wikipedia/commons/thumb/d/d4/Long_Beach_1983.jpg/250px-Long_Beach_1983.jpg",
    "trackType": "Street circuit",
    "direction": "Clockwise",
    "location": "Long Beach",
    "country": "United States",
    "lastLengthKm": "3.275",
    "lastLengthMi": "2.035",
    "turns": "18",
    "grandPrixes": [
      "United States Grand Prix West"
    ],
    "seasons": [
      1976,
      1977,
      1978,
      1979,
      1980,
      1981,
      1982,
      1983
    ],
    "grandPrixesHeld": "8"
  },
  {
    "name": "Lusail International Circuit ",
    "map": "https://upload.wikimedia.org/wikipedia/commons/thumb/c/c7/Lusail_International_Circuit_2023.svg/250px-Lusail_International_Circuit_2023.svg.png",
    "trackType": "Race circuit",
    "direction": "Clockwise",
    "location": "Lusail",
    "country": "Qatar",
    "lastLengthKm": "5.419",
    "lastLengthMi": "3.367",
    "turns": "16",
    "grandPrixes": [
      "Qatar Grand Prix"
    ],
    "seasons": [
      2021,
      2023,
      2024
    ],
    "grandPrixesHeld": "3"
  },
  {
    "name": "Marina Bay Street Circuit ",
    "map": "https://upload.wikimedia.org/wikipedia/commons/thumb/8/8b/Marina_Bay_circuit_2023.svg/250px-Marina_Bay_circuit_2023.svg.png",
    "trackType": "Street circuit",
    "direction": "Anti-clockwise",
    "location": "Marina Bay",
    "country": "Singapore",
    "lastLengthKm": "4.940",
    "lastLengthMi": "3.070",
    "turns": "19",
    "grandPrixes": [
      "Singapore Grand Prix"
    ],
    "seasons": [
      2008,
      2009,
      2010,
      2011,
      2012,
      2013,
      2014,
      2015,
      2016,
      2017,
      2018,
      2019,
      2022,
      2023,
      2024
    ],
    "grandPrixesHeld": "15"
  },
  {
    "name": "Miami International Autodrome ",
    "map": "https://upload.wikimedia.org/wikipedia/commons/thumb/4/49/Hard_Rock_Stadium_Circuit_2022.svg/250px-Hard_Rock_Stadium_Circuit_2022.svg.png",
    "trackType": "Street circuit",
    "direction": "Anti-clockwise",
    "location": "Miami Gardens",
    "country": "United States",
    "lastLengthKm": "5.412",
    "lastLengthMi": "3.363",
    "turns": "18",
    "grandPrixes": [
      "Miami Grand Prix"
    ],
    "seasons": [
      2022,
      2023,
      2024,
      2025
    ],
    "grandPrixesHeld": "4"
  },
  {
    "name": "Montjuic circuit",
    "map": "https://upload.wikimedia.org/wikipedia/commons/thumb/b/b7/Montju%C3%AFc_circuit.svg/250px-Montju%C3%AFc_circuit.svg.png",
    "trackType": "Street circuit",
    "direction": "Anti-clockwise",
    "location": "Barcelona",
    "country": "Spain",
    "lastLengthKm": "3.791",
    "lastLengthMi": "2.356",
    "turns": "18",
    "grandPrixes": [
      "Spanish Grand Prix"
    ],
    "seasons": [
      1969,
      1971,
      1973,
      1975
    ],
    "grandPrixesHeld": "4"
  },
  {
    "name": "Mosport International Raceway",
    "map": "https://upload.wikimedia.org/wikipedia/commons/thumb/c/cb/Mosport.svg/250px-Mosport.svg.png",
    "trackType": "Race circuit",
    "direction": "Clockwise",
    "location": "Bowmanville",
    "country": "Canada",
    "lastLengthKm": "3.957",
    "lastLengthMi": "2.459",
    "turns": "10",
    "grandPrixes": [
      "Canadian Grand Prix"
    ],
    "seasons": [
      1967,
      1969,
      1971,
      1972,
      1973,
      1974,
      1976,
      1977
    ],
    "grandPrixesHeld": "8"
  },
  {
    "name": "Nivelles-Baulers",
    "map": "https://upload.wikimedia.org/wikipedia/commons/thumb/0/0f/Circuit_Nivelles-Baulers.png/250px-Circuit_Nivelles-Baulers.png",
    "trackType": "Race circuit",
    "direction": "Clockwise",
    "location": "Nivelles",
    "country": "Belgium",
    "lastLengthKm": "3.724",
    "lastLengthMi": "2.314",
    "turns": "7",
    "grandPrixes": [
      "Belgian Grand Prix"
    ],
    "seasons": [
      1972,
      1974
    ],
    "grandPrixesHeld": "2"
  },
  {
    "name": "Nurburgring",
    "map": "https://upload.wikimedia.org/wikipedia/commons/thumb/7/76/N%C3%BCrburgring_-_Grand-Prix-Strecke.svg/250px-N%C3%BCrburgring_-_Grand-Prix-Strecke.svg.png",
    "trackType": "Race circuit",
    "direction": "Clockwise",
    "location": "Nurburg",
    "country": "Germany",
    "lastLengthKm": "5.148",
    "lastLengthMi": "3.199",
    "turns": "15",
    "grandPrixes": [
      "German Grand Prix",
      "European Grand Prix",
      "Luxembourg Grand Prix",
      "Eifel Grand Prix"
    ],
    "seasons": [
      1951,
      1952,
      1953,
      1954,
      1956,
      1957,
      1958,
      1961,
      1962,
      1963,
      1964,
      1965,
      1966,
      1967,
      1968,
      1969,
      1971,
      1972,
      1973,
      1974,
      1975,
      1976,
      1984,
      1985,
      1995,
      1996,
      1997,
      1998,
      1999,
      2000,
      2001,
      2002,
      2003,
      2004,
      2005,
      2006,
      2007,
      2009,
      2011,
      2013,
      2020
    ],
    "grandPrixesHeld": "41"
  },
  {
    "name": "Pescara Circuit",
    "map": "https://upload.wikimedia.org/wikipedia/commons/thumb/a/a8/Circuit_Pescara.svg/250px-Circuit_Pescara.svg.png",
    "trackType": "Road circuit",
    "direction": "Clockwise",
    "location": "Pescara",
    "country": "Italy",
    "lastLengthKm": "25.800",
    "lastLengthMi": "16.031",
    "turns": "24*",
    "grandPrixes": [
      "Pescara Grand Prix"
    ],
    "seasons": [
      1957
    ],
    "grandPrixesHeld": "1"
  },
  {
    "name": "Phoenix Street Circuit",
    "map": "https://upload.wikimedia.org/wikipedia/commons/thumb/f/fa/Phoenix_Grand_Prix_Route_-_1991.svg/250px-Phoenix_Grand_Prix_Route_-_1991.svg.png",
    "trackType": "Street circuit",
    "direction": "Anti-clockwise",
    "location": "Phoenix",
    "country": "United States",
    "lastLengthKm": "3.720",
    "lastLengthMi": "2.312",
    "turns": "12",
    "grandPrixes": [
      "United States Grand Prix"
    ],
    "seasons": [
      1989,
      1990,
      1991
    ],
    "grandPrixesHeld": "3"
  },
  {
    "name": "Prince George Circuit",
    "map": "https://upload.wikimedia.org/wikipedia/commons/thumb/2/2d/Prince_George_Circuit.svg/250px-Prince_George_Circuit.svg.png",
    "trackType": "Race circuit",
    "direction": "Clockwise",
    "location": "East London",
    "country": "South Africa",
    "lastLengthKm": "3.920",
    "lastLengthMi": "2.436",
    "turns": "8",
    "grandPrixes": [
      "South African Grand Prix"
    ],
    "seasons": [
      1962,
      1963,
      1965
    ],
    "grandPrixesHeld": "3"
  },
  {
    "name": "Red Bull Ring ",
    "map": "https://upload.wikimedia.org/wikipedia/commons/thumb/4/4e/Spielberg_bare_map_numbers_contextless_2021_corner_names.svg/250px-Spielberg_bare_map_numbers_contextless_2021_corner_names.svg.png",
    "trackType": "Race circuit",
    "direction": "Clockwise",
    "location": "Spielberg",
    "country": "Austria",
    "lastLengthKm": "4.318",
    "lastLengthMi": "2.683",
    "turns": "10",
    "grandPrixes": [
      "Austrian Grand Prix",
      "Styrian Grand Prix"
    ],
    "seasons": [
      1970,
      1971,
      1972,
      1973,
      1974,
      1975,
      1976,
      1977,
      1978,
      1979,
      1980,
      1981,
      1982,
      1983,
      1984,
      1985,
      1986,
      1987,
      1997,
      1998,
      1999,
      2000,
      2001,
      2002,
      2003,
      2014,
      2015,
      2016,
      2017,
      2018,
      2019,
      2020,
      2021,
      2022,
      2023,
      2024
    ],
    "grandPrixesHeld": "38"
  },
  {
    "name": "Riverside International Raceway",
    "map": "https://upload.wikimedia.org/wikipedia/commons/thumb/5/5d/Riverside_International_Raceway_1967.svg/250px-Riverside_International_Raceway_1967.svg.png",
    "trackType": "Race circuit",
    "direction": "Clockwise",
    "location": "Moreno Valley",
    "country": "United States",
    "lastLengthKm": "5.271",
    "lastLengthMi": "3.275",
    "turns": "9",
    "grandPrixes": [
      "United States Grand Prix"
    ],
    "seasons": [
      1960
    ],
    "grandPrixesHeld": "1"
  },
  {
    "name": "Rouen-Les-Essarts",
    "map": "https://upload.wikimedia.org/wikipedia/commons/thumb/4/45/Rouen_track_layout_1955-1971.gif/250px-Rouen_track_layout_1955-1971.gif",
    "trackType": "Road circuit",
    "direction": "Clockwise",
    "location": "Orival",
    "country": "France",
    "lastLengthKm": "6.542",
    "lastLengthMi": "4.065",
    "turns": "13",
    "grandPrixes": [
      "French Grand Prix"
    ],
    "seasons": [
      1952,
      1957,
      1962,
      1964,
      1968
    ],
    "grandPrixesHeld": "5"
  },
  {
    "name": "Scandinavian Raceway",
    "map": "https://upload.wikimedia.org/wikipedia/commons/thumb/b/bf/Scandinavian_Raceway_1978.svg/250px-Scandinavian_Raceway_1978.svg.png",
    "trackType": "Race circuit",
    "direction": "Clockwise",
    "location": "Anderstorp",
    "country": "Sweden",
    "lastLengthKm": "4.031",
    "lastLengthMi": "2.505",
    "turns": "8",
    "grandPrixes": [
      "Swedish Grand Prix"
    ],
    "seasons": [
      1973,
      1974,
      1975,
      1976,
      1977,
      1978
    ],
    "grandPrixesHeld": "6"
  },
  {
    "name": "Sebring Raceway",
    "map": "https://upload.wikimedia.org/wikipedia/commons/thumb/3/39/Sebring_International_Raceway_-_Historical_%281952%29.svg/250px-Sebring_International_Raceway_-_Historical_%281952%29.svg.png",
    "trackType": "Road circuit",
    "direction": "Clockwise",
    "location": "Sebring",
    "country": "United States",
    "lastLengthKm": "8.356",
    "lastLengthMi": "5.192",
    "turns": "12",
    "grandPrixes": [
      "United States Grand Prix"
    ],
    "seasons": [
      1959
    ],
    "grandPrixesHeld": "1"
  },
  {
    "name": "Sepang International Circuit",
    "map": "https://upload.wikimedia.org/wikipedia/commons/thumb/6/67/Sepang.svg/250px-Sepang.svg.png",
    "trackType": "Race circuit",
    "direction": "Clockwise",
    "location": "Sepang",
    "country": "Malaysia",
    "lastLengthKm": "5.543",
    "lastLengthMi": "3.444",
    "turns": "15",
    "grandPrixes": [
      "Malaysian Grand Prix"
    ],
    "seasons": [
      1999,
      2000,
      2001,
      2002,
      2003,
      2004,
      2005,
      2006,
      2007,
      2008,
      2009,
      2010,
      2011,
      2012,
      2013,
      2014,
      2015,
      2016,
      2017
    ],
    "grandPrixesHeld": "19"
  },
  {
    "name": "Shanghai International Circuit ",
    "map": "https://upload.wikimedia.org/wikipedia/commons/thumb/1/14/Shanghai_International_Racing_Circuit_track_map.svg/250px-Shanghai_International_Racing_Circuit_track_map.svg.png",
    "trackType": "Race circuit",
    "direction": "Clockwise",
    "location": "Shanghai",
    "country": "China",
    "lastLengthKm": "5.451",
    "lastLengthMi": "3.387",
    "turns": "16",
    "grandPrixes": [
      "Chinese Grand Prix"
    ],
    "seasons": [
      2004,
      2005,
      2006,
      2007,
      2008,
      2009,
      2010,
      2011,
      2012,
      2013,
      2014,
      2015,
      2016,
      2017,
      2018,
      2019,
      2024,
      2025
    ],
    "grandPrixesHeld": "18"
  },
  {
    "name": "Silverstone Circuit ",
    "map": "https://upload.wikimedia.org/wikipedia/commons/thumb/0/0c/Silverstone_Circuit_vector_map.png/250px-Silverstone_Circuit_vector_map.png",
    "trackType": "Race circuit",
    "direction": "Clockwise",
    "location": "Silverstone",
    "country": "United Kingdom",
    "lastLengthKm": "5.891",
    "lastLengthMi": "3.660",
    "turns": "18",
    "grandPrixes": [
      "British Grand Prix",
      "70th Anniversary Grand Prix"
    ],
    "seasons": [
      1950,
      1951,
      1952,
      1953,
      1954,
      1956,
      1958,
      1960,
      1963,
      1965,
      1967,
      1969,
      1971,
      1973,
      1975,
      1977,
      1979,
      1981,
      1983,
      1985,
      1987,
      1988,
      1989,
      1990,
      1991,
      1992,
      1993,
      1994,
      1995,
      1996,
      1997,
      1998,
      1999,
      2000,
      2001,
      2002,
      2003,
      2004,
      2005,
      2006,
      2007,
      2008,
      2009,
      2010,
      2011,
      2012,
      2013,
      2014,
      2015,
      2016,
      2017,
      2018,
      2019,
      2020,
      2021,
      2022,
      2023,
      2024
    ],
    "grandPrixesHeld": "59"
  },
  {
    "name": "Sochi Autodrom",
    "map": "https://upload.wikimedia.org/wikipedia/commons/thumb/d/d3/Circuit_Sochi.svg/250px-Circuit_Sochi.svg.png",
    "trackType": "Race circuit",
    "direction": "Clockwise",
    "location": "Sochi",
    "country": "Russia",
    "lastLengthKm": "5.848",
    "lastLengthMi": "3.634",
    "turns": "15",
    "grandPrixes": [
      "Russian Grand Prix"
    ],
    "seasons": [
      2014,
      2015,
      2016,
      2017,
      2018,
      2019,
      2020,
      2021
    ],
    "grandPrixesHeld": "8"
  },
  {
    "name": "Suzuka International Racing Course ",
    "map": "https://upload.wikimedia.org/wikipedia/commons/thumb/e/ec/Suzuka_circuit_map--2005.svg/250px-Suzuka_circuit_map--2005.svg.png",
    "trackType": "Race circuit",
    "direction": "Part clockwise and part anti-clockwise (figure eight)",
    "location": "Suzuka",
    "country": "Japan",
    "lastLengthKm": "5.807",
    "lastLengthMi": "3.608",
    "turns": "18",
    "grandPrixes": [
      "Japanese Grand Prix"
    ],
    "seasons": [
      1987,
      1988,
      1989,
      1990,
      1991,
      1992,
      1993,
      1994,
      1995,
      1996,
      1997,
      1998,
      1999,
      2000,
      2001,
      2002,
      2003,
      2004,
      2005,
      2006,
      2009,
      2010,
      2011,
      2012,
      2013,
      2014,
      2015,
      2016,
      2017,
      2018,
      2019,
      2022,
      2023,
      2024,
      2025
    ],
    "grandPrixesHeld": "35"
  },
  {
    "name": "TI Circuit Aida",
    "map": "https://upload.wikimedia.org/wikipedia/commons/thumb/b/b4/Circuit_TI_%28Aida%29.png/250px-Circuit_TI_%28Aida%29.png",
    "trackType": "Race circuit",
    "direction": "Clockwise",
    "location": "Mimasaka",
    "country": "Japan",
    "lastLengthKm": "3.703",
    "lastLengthMi": "2.301",
    "turns": "11",
    "grandPrixes": [
      "Pacific Grand Prix"
    ],
    "seasons": [
      1994,
      1995
    ],
    "grandPrixesHeld": "2"
  },
  {
    "name": "Valencia Street Circuit",
    "map": "https://upload.wikimedia.org/wikipedia/commons/thumb/f/fd/Circuit_Valencia_street.svg/250px-Circuit_Valencia_street.svg.png",
    "trackType": "Street circuit",
    "direction": "Clockwise",
    "location": "Valencia",
    "country": "Spain",
    "lastLengthKm": "5.419",
    "lastLengthMi": "3.367",
    "turns": "25",
    "grandPrixes": [
      "European Grand Prix"
    ],
    "seasons": [
      2008,
      2009,
      2010,
      2011,
      2012
    ],
    "grandPrixesHeld": "5"
  },
  {
    "name": "Watkins Glen International",
    "map": "https://upload.wikimedia.org/wikipedia/commons/thumb/5/59/Watkins_Glen_1975-1983.png/250px-Watkins_Glen_1975-1983.png",
    "trackType": "Race circuit",
    "direction": "Clockwise",
    "location": "Watkins Glen",
    "country": "United States",
    "lastLengthKm": "5.430",
    "lastLengthMi": "3.374",
    "turns": "10",
    "grandPrixes": [
      "United States Grand Prix"
    ],
    "seasons": [
      1961,
      1962,
      1963,
      1964,
      1965,
      1966,
      1967,
      1968,
      1969,
      1970,
      1971,
      1972,
      1973,
      1974,
      1975,
      1976,
      1977,
      1978,
      1979,
      1980
    ],
    "grandPrixesHeld": "20"
  },
  {
    "name": "Yas Marina Circuit ",
    "map": "https://upload.wikimedia.org/wikipedia/commons/thumb/b/b0/Yas_Marina_Circuit.png/250px-Yas_Marina_Circuit.png",
    "trackType": "Race circuit",
    "direction": "Anti-clockwise",
    "location": "Abu Dhabi",
    "country": "United Arab Emirates",
    "lastLengthKm": "5.281",
    "lastLengthMi": "3.281",
    "turns": "15",
    "grandPrixes": [
      "Abu Dhabi Grand Prix"
    ],
    "seasons": [
      2009,
      2010,
      2011,
      2012,
      2013,
      2014,
      2015,
      2016,
      2017,
      2018,
      2019,
      2020,
      2021,
      2022,
      2023,
      2024
    ],
    "grandPrixesHeld": "16"
  },
  {
    "name": "Zeltweg Airfield",
    "map": "https://upload.wikimedia.org/wikipedia/commons/thumb/a/a4/Circuit_Zeltweg.png/250px-Circuit_Zeltweg.png",
    "trackType": "Road circuit",
    "direction": "Clockwise",
    "location": "Zeltweg",
    "country": "Austria",
    "lastLengthKm": "3.186",
    "lastLengthMi": "1.980",
    "turns": "4",
    "grandPrixes": [
      "Austrian Grand Prix"
    ],
    "seasons": [
      1964
    ],
    "grandPrixesHeld": "1"
  }
]